{
  "formatVersion": 1,
  "database": {
    "version": 1,
    "identityHash": "fc86eabf6662a08a0184898db0133800",
    "entities": [
      {
        "tableName": "document_table",
        "createSql": "CREATE TABLE IF NOT EXISTS `${TABLE_NAME}` (`id` INTEGER PRIMARY KEY AUTOINCREMENT NOT NULL, `number` TEXT NOT NULL, `type` TEXT NOT NULL, `dateMillis` INTEGER NOT NULL, `category` TEXT NOT NULL, `amount` REAL NOT NULL, `comment` TEXT NOT NULL, `isFromTroopAccount` INTEGER NOT NULL, `isFromTravelVoucher` INTEGER NOT NULL, `campId` INTEGER NOT NULL)",
        "fields": [
          {
            "fieldPath": "id",
            "columnName": "id",
            "affinity": "INTEGER",
            "notNull": true
          },
          {
            "fieldPath": "number",
            "columnName": "number",
            "affinity": "TEXT",
            "notNull": true
          },
          {
            "fieldPath": "type",
            "columnName": "type",
            "affinity": "TEXT",
            "notNull": true
          },
          {
            "fieldPath": "dateMillis",
            "columnName": "dateMillis",
            "affinity": "INTEGER",
            "notNull": true
          },
          {
            "fieldPath": "category",
            "columnName": "category",
            "affinity": "TEXT",
            "notNull": true
          },
          {
            "fieldPath": "amount",
            "columnName": "amount",
            "affinity": "REAL",
            "notNull": true
          },
          {
            "fieldPath": "comment",
            "columnName": "comment",
            "affinity": "TEXT",
            "notNull": true
          },
          {
            "fieldPath": "isFromTroopAccount",
            "columnName": "isFromTroopAccount",
            "affinity": "INTEGER",
            "notNull": true
          },
          {
            "fieldPath": "isFromTravelVoucher",
            "columnName": "isFromTravelVoucher",
            "affinity": "INTEGER",
            "notNull": true
          },
          {
            "fieldPath": "campId",
            "columnName": "campId",
            "affinity": "INTEGER",
            "notNull": true
          }
        ],
        "primaryKey": {
          "columnNames": [
            "id"
          ],
          "autoGenerate": true
        },
        "indices": [],
        "foreignKeys": []
      },
      {
        "tableName": "camp_table",
        "createSql": "CREATE TABLE IF NOT EXISTS `${TABLE_NAME}` (`id` INTEGER PRIMARY KEY AUTOINCREMENT NOT NULL, `name` TEXT NOT NULL, `budget` REAL NOT NULL, `startDateMillis` INTEGER NOT NULL, `endDateMillis` INTEGER NOT NULL, `isActive` INTEGER NOT NULL)",
        "fields": [
          {
            "fieldPath": "id",
            "columnName": "id",
            "affinity": "INTEGER",
            "notNull": true
          },
          {
            "fieldPath": "name",
            "columnName": "name",
            "affinity": "TEXT",
            "notNull": true
          },
          {
            "fieldPath": "budget",
            "columnName": "budget",
            "affinity": "REAL",
            "notNull": true
          },
          {
            "fieldPath": "startDateMillis",
            "columnName": "startDateMillis",
            "affinity": "INTEGER",
            "notNull": true
          },
          {
            "fieldPath": "endDateMillis",
            "columnName": "endDateMillis",
            "affinity": "INTEGER",
            "notNull": true
          },
          {
            "fieldPath": "isActive",
            "columnName": "isActive",
            "affinity": "INTEGER",
            "notNull": true
          }
        ],
        "primaryKey": {
          "columnNames": [
            "id"
          ],
          "autoGenerate": true
        },
        "indices": [],
        "foreignKeys": []
      }
    ],
    "views": [],
    "setupQueries": [
      "CREATE TABLE IF NOT EXISTS room_master_table (id INTEGER PRIMARY KEY,identity_hash TEXT)",
      "INSERT OR REPLACE INTO room_master_table (id,identity_hash) VALUES(42, 'fc86eabf6662a08a0184898db0133800')"
    ]
  }
}